azure_graph_toolkit/__init__.py
azure_graph_toolkit/config.py
azure_graph_toolkit/graph_auth.py
azure_graph_toolkit/graph_utils.py
azure_graph_toolkit/utils/__init__.py
azure_graph_toolkit/utils/decorators.py
test/__init__.py
test/unit-test.py
azure_graph_toolkit-1.1.1.dist-info/LICENSE
azure_graph_toolkit-1.1.1.dist-info/METADATA
azure_graph_toolkit-1.1.1.dist-info/WHEEL
azure_graph_toolkit-1.1.1.dist-info/top_level.txt
azure_graph_toolkit-1.1.1.dist-info/RECORD
