Metadata-Version: 2.1
Name: azure-graph-toolkit
Version: 1.1.1
Summary: Lightweight python library for easily managing Azure AD (Entra ID) users and groups through the Graph API.
Home-page: https://github.com/Ivanodib/azure-graph-toolkit
Author: Ivano Dibenedetto
Author-email: ivano.dibenedetto7@gmail.com
Classifier: License :: OSI Approved :: MIT License
Classifier: Programming Language :: Python :: 3
Classifier: Operating System :: OS Independent
License-File: LICENSE
